acenta/__init__.py
acenta/cli.py
acenta/agents/base.py
acenta/agents/runner.py
acenta/agents/simple_openai_agent.py
acenta/core/__init__.py
acenta/core/base_protocol.py
acenta/core/base_protocol_adapter.py
acenta/core/client.py
acenta/core/connector.py
acenta/core/network.py
acenta/core/system_commands.py
acenta/launchers/__init__.py
acenta/launchers/discovery_connector.py
acenta/launchers/network_launcher.py
acenta/launchers/terminal_console.py
acenta/models/__init__.py
acenta/models/manifest.py
acenta/models/message_thread.py
acenta/models/messages.py
acenta/models/network_config.py
acenta/models/network_profile.py
acenta/models/tool.py
acenta/protocols/__init__.py
acenta/protocols/communication/__init__.py
acenta/protocols/communication/simple_messaging/__init__.py
acenta/protocols/communication/simple_messaging/adapter.py
acenta/protocols/communication/simple_messaging/protocol.py
acenta/protocols/discovery/__init__.py
acenta/protocols/discovery/agent_discovery/__init__.py
acenta/protocols/discovery/agent_discovery/adapter.py
acenta/protocols/discovery/agent_discovery/protocol.py
acenta/utils/__init__.py
acenta/utils/message_util.py
acenta/utils/network_discovey.py
acenta/utils/protocol_loaders.py
acenta-0.4.0.dist-info/licenses/LICENSE
acenta-0.4.0.dist-info/METADATA
acenta-0.4.0.dist-info/WHEEL
acenta-0.4.0.dist-info/entry_points.txt
acenta-0.4.0.dist-info/top_level.txt
acenta-0.4.0.dist-info/RECORD
